{"823--114": {"c": 19, "elat": 54.93333333333333, "unknown": 6.0, "slat": 54.86666666666667, "micro_company": 10.0, "elon": -7.533333333333333, "small_company": 3.0, "sc": 1, "slon": -7.6, "s_unknown": 1.0}, "805--127": {"c": 3, "elat": 53.733333333333334, "unknown": 2.0, "slat": 53.666666666666664, "micro_company": 1.0, "elon": -8.4, "sc": 1, "s_micro_company": 1.0, "slon": -8.466666666666667}, "825--116": {"c": 64, "elat": 55.06666666666667, "unknown": 15.0, "slat": 55.0, "micro_company": 39.0, "elon": -7.666666666666667, "medium_company": 1.0, "small_company": 9.0, "sc": 1, "s_micro_company": 1.0, "slon": -7.733333333333333}, "805--123": {"large_company": 1.0, "c": 248, "elat": 53.733333333333334, "unknown": 60.0, "slat": 53.666666666666664, "micro_company": 158.0, "elon": -8.133333333333333, "medium_company": 1.0, "small_company": 28.0, "sc": 4, "s_micro_company": 1.0, "slon": -8.2, "s_unknown": 3.0}, "808--134": {"c": 6, "elat": 53.93333333333333, "unknown": 2.0, "slat": 53.86666666666667, "micro_company": 4.0, "elon": -8.866666666666667, "sc": 1, "s_micro_company": 1.0, "slon": -8.933333333333334}, "790--131": {"c": 47, "elat": 52.733333333333334, "unknown": 10.0, "slat": 52.666666666666664, "micro_company": 31.0, "elon": -8.666666666666666, "small_company": 6.0, "sc": 1, "slon": -8.733333333333333, "s_unknown": 1.0}, "825--111": {"large_company": 2.0, "c": 49, "elat": 55.06666666666667, "unknown": 13.0, "slat": 55.0, "micro_company": 27.0, "elon": -7.333333333333333, "medium_company": 1.0, "small_company": 6.0, "sc": 1, "slon": -7.4, "s_unknown": 1.0}, "808--139": {"c": 167, "elat": 53.93333333333333, "unknown": 65.0, "slat": 53.86666666666667, "micro_company": 88.0, "elon": -9.2, "medium_company": 1.0, "small_company": 13.0, "sc": 9, "slon": -9.266666666666667, "s_unknown": 9.0}, "823--119": {"c": 255, "elat": 54.93333333333333, "unknown": 126.0, "slat": 54.86666666666667, "micro_company": 110.0, "elon": -7.866666666666666, "medium_company": 4.0, "small_company": 15.0, "sc": 11, "s_micro_company": 1.0, "slon": -7.933333333333334, "s_unknown": 10.0}, "805--128": {"c": 26, "elat": 53.733333333333334, "unknown": 2.0, "slat": 53.666666666666664, "micro_company": 22.0, "elon": -8.466666666666667, "small_company": 2.0, "sc": 1, "slon": -8.533333333333333, "s_unknown": 1.0}, "809--122": {"c": 20, "elat": 54.0, "unknown": 2.0, "slat": 53.93333333333333, "micro_company": 16.0, "elon": -8.066666666666666, "small_company": 2.0, "sc": 1, "slon": -8.133333333333333, "s_unknown": 1.0}, "795--132": {"c": 44, "elat": 53.06666666666667, "unknown": 11.0, "slat": 53.0, "micro_company": 27.0, "elon": -8.733333333333333, "medium_company": 2.0, "small_company": 4.0, "sc": 2, "s_micro_company": 1.0, "slon": -8.8, "s_unknown": 1.0}, "819--126": {"large_company": 3.0, "c": 181, "elat": 54.666666666666664, "unknown": 34.0, "slat": 54.6, "micro_company": 88.0, "elon": -8.333333333333334, "medium_company": 15.0, "small_company": 41.0, "sc": 3, "s_micro_company": 2.0, "slon": -8.4, "s_unknown": 1.0}, "819--124": {"c": 25, "elat": 54.666666666666664, "unknown": 7.0, "slat": 54.6, "micro_company": 18.0, "elon": -8.2, "sc": 1, "s_micro_company": 1.0, "slon": -8.266666666666667}, "795--139": {"c": 53, "elat": 53.06666666666667, "unknown": 11.0, "slat": 53.0, "micro_company": 32.0, "elon": -9.2, "medium_company": 1.0, "small_company": 9.0, "sc": 2, "slon": -9.266666666666667, "s_unknown": 2.0}, "807--139": {"large_company": 5.0, "c": 559, "elat": 53.86666666666667, "unknown": 111.0, "slat": 53.8, "micro_company": 336.0, "elon": -9.2, "medium_company": 17.0, "small_company": 90.0, "sc": 9, "s_micro_company": 3.0, "slon": -9.266666666666667, "s_unknown": 6.0}, "819--121": {"large_company": 1.0, "c": 212, "elat": 54.666666666666664, "unknown": 51.0, "slat": 54.6, "micro_company": 116.0, "elon": -8.0, "medium_company": 6.0, "small_company": 38.0, "sc": 1, "slon": -8.066666666666666, "s_unknown": 1.0}, "808--128": {"c": 100, "elat": 53.93333333333333, "unknown": 15.0, "slat": 53.86666666666667, "micro_company": 64.0, "elon": -8.466666666666667, "medium_company": 7.0, "small_company": 14.0, "sc": 2, "s_micro_company": 1.0, "slon": -8.533333333333333, "s_unknown": 1.0}, "807--138": {"c": 80, "elat": 53.86666666666667, "unknown": 15.0, "slat": 53.8, "micro_company": 55.0, "elon": -9.133333333333333, "medium_company": 1.0, "small_company": 9.0, "sc": 1, "slon": -9.2, "s_unknown": 1.0}, "796--132": {"large_company": 1.0, "c": 274, "elat": 53.13333333333333, "unknown": 71.0, "slat": 53.06666666666667, "micro_company": 176.0, "elon": -8.733333333333333, "medium_company": 6.0, "small_company": 20.0, "sc": 3, "s_micro_company": 2.0, "slon": -8.8, "s_unknown": 1.0}, "790--129": {"c": 89, "elat": 52.733333333333334, "unknown": 22.0, "slat": 52.666666666666664, "micro_company": 58.0, "elon": -8.533333333333333, "medium_company": 2.0, "small_company": 7.0, "sc": 4, "s_micro_company": 3.0, "slon": -8.6, "s_unknown": 1.0}, "824--116": {"large_company": 1.0, "c": 509, "elat": 55.0, "unknown": 134.0, "slat": 54.93333333333333, "micro_company": 293.0, "elon": -7.666666666666667, "medium_company": 11.0, "small_company": 70.0, "sc": 9, "s_micro_company": 1.0, "slon": -7.733333333333333, "s_unknown": 8.0}, "810--117": {"c": 82, "elat": 54.06666666666667, "unknown": 10.0, "slat": 54.0, "micro_company": 63.0, "elon": -7.733333333333333, "medium_company": 1.0, "small_company": 8.0, "sc": 3, "s_micro_company": 2.0, "slon": -7.8, "s_unknown": 1.0}, "794--118": {"c": 1, "elat": 53.0, "unknown": 1.0, "slat": 52.93333333333333, "elon": -7.8, "s_unknown": 1.0, "sc": 1, "slon": -7.866666666666666}, "809--124": {"large_company": 2.0, "c": 131, "elat": 54.0, "unknown": 28.0, "slat": 53.93333333333333, "micro_company": 85.0, "elon": -8.2, "medium_company": 2.0, "small_company": 14.0, "sc": 5, "s_micro_company": 1.0, "slon": -8.266666666666667, "s_unknown": 4.0}, "825--125": {"c": 21, "elat": 55.06666666666667, "unknown": 7.0, "slat": 55.0, "micro_company": 10.0, "elon": -8.266666666666667, "medium_company": 2.0, "small_company": 2.0, "sc": 3, "s_micro_company": 2.0, "slon": -8.333333333333334, "s_unknown": 1.0}, "825--126": {"c": 2, "elat": 55.06666666666667, "unknown": 1.0, "slat": 55.0, "micro_company": 1.0, "elon": -8.333333333333334, "s_unknown": 1.0, "sc": 1, "slon": -8.4}, "817--122": {"c": 155, "elat": 54.53333333333333, "unknown": 39.0, "slat": 54.46666666666667, "micro_company": 92.0, "elon": -8.066666666666666, "medium_company": 10.0, "small_company": 14.0, "sc": 2, "slon": -8.133333333333333, "s_unknown": 2.0}, "805--135": {"c": 49, "elat": 53.733333333333334, "unknown": 14.0, "slat": 53.666666666666664, "micro_company": 31.0, "elon": -8.933333333333334, "small_company": 4.0, "sc": 4, "s_micro_company": 2.0, "slon": -9.0, "s_unknown": 2.0}, "805--134": {"c": 341, "elat": 53.733333333333334, "unknown": 64.0, "slat": 53.666666666666664, "micro_company": 238.0, "elon": -8.866666666666667, "medium_company": 5.0, "small_company": 34.0, "sc": 7, "s_micro_company": 6.0, "slon": -8.933333333333334, "s_unknown": 1.0}, "821--117": {"c": 14, "elat": 54.8, "unknown": 2.0, "slat": 54.733333333333334, "micro_company": 10.0, "elon": -7.733333333333333, "medium_company": 1.0, "small_company": 1.0, "sc": 1, "s_micro_company": 1.0, "slon": -7.8}, "791--131": {"c": 34, "elat": 52.8, "unknown": 13.0, "slat": 52.733333333333334, "micro_company": 19.0, "elon": -8.666666666666666, "small_company": 2.0, "sc": 1, "s_micro_company": 1.0, "slon": -8.733333333333333}, "808--124": {"c": 18, "elat": 53.93333333333333, "unknown": 5.0, "slat": 53.86666666666667, "micro_company": 11.0, "elon": -8.2, "s_unknown": 1.0, "sc": 1, "slon": -8.266666666666667, "small_company": 2.0}, "791--133": {"c": 82, "elat": 52.8, "unknown": 15.0, "slat": 52.733333333333334, "micro_company": 57.0, "elon": -8.8, "small_company": 10.0, "sc": 1, "slon": -8.866666666666667, "s_unknown": 1.0}, "811--137": {"large_company": 7.0, "c": 223, "elat": 54.13333333333333, "unknown": 38.0, "slat": 54.06666666666667, "micro_company": 135.0, "elon": -9.066666666666666, "medium_company": 2.0, "small_company": 41.0, "sc": 2, "slon": -9.133333333333333, "s_unknown": 2.0}, "813--123": {"c": 7, "elat": 54.266666666666666, "unknown": 3.0, "slat": 54.2, "micro_company": 4.0, "elon": -8.133333333333333, "s_unknown": 1.0, "sc": 1, "slon": -8.2}, "791--134": {"c": 4, "elat": 52.8, "slat": 52.733333333333334, "micro_company": 4.0, "elon": -8.866666666666667, "sc": 1, "s_micro_company": 1.0, "slon": -8.933333333333334}, "822--116": {"c": 49, "elat": 54.86666666666667, "unknown": 14.0, "slat": 54.8, "micro_company": 25.0, "elon": -7.666666666666667, "medium_company": 1.0, "small_company": 9.0, "sc": 5, "s_micro_company": 1.0, "slon": -7.733333333333333, "s_unknown": 4.0}, "822--117": {"c": 2, "elat": 54.86666666666667, "unknown": 1.0, "slat": 54.8, "micro_company": 1.0, "elon": -7.733333333333333, "sc": 1, "s_micro_company": 1.0, "slon": -7.8}, "800--133": {"c": 259, "elat": 53.4, "unknown": 69.0, "slat": 53.333333333333336, "micro_company": 164.0, "elon": -8.8, "medium_company": 8.0, "small_company": 18.0, "sc": 6, "s_micro_company": 4.0, "slon": -8.866666666666667, "s_unknown": 2.0}, "800--130": {"c": 38, "elat": 53.4, "unknown": 3.0, "slat": 53.333333333333336, "micro_company": 32.0, "elon": -8.6, "small_company": 3.0, "sc": 1, "slon": -8.666666666666666, "s_unknown": 1.0}, "800--137": {"c": 127, "elat": 53.4, "unknown": 21.0, "slat": 53.333333333333336, "micro_company": 86.0, "elon": -9.066666666666666, "medium_company": 3.0, "s_unknown": 4.0, "sc": 5, "s_micro_company": 1.0, "slon": -9.133333333333333, "small_company": 17.0}, "800--134": {"c": 227, "elat": 53.4, "unknown": 45.0, "slat": 53.333333333333336, "micro_company": 150.0, "elon": -8.866666666666667, "medium_company": 3.0, "small_company": 29.0, "sc": 2, "s_micro_company": 2.0, "slon": -8.933333333333334}, "803--149": {"c": 31, "elat": 53.6, "unknown": 5.0, "slat": 53.53333333333333, "micro_company": 18.0, "elon": -9.866666666666667, "small_company": 8.0, "sc": 1, "s_micro_company": 1.0, "slon": -9.933333333333334}, "812--130": {"large_company": 1.0, "c": 189, "elat": 54.2, "unknown": 59.0, "slat": 54.13333333333333, "micro_company": 101.0, "elon": -8.6, "medium_company": 1.0, "small_company": 27.0, "sc": 8, "s_micro_company": 1.0, "slon": -8.666666666666666, "s_unknown": 7.0}, "808--133": {"c": 1, "elat": 53.93333333333333, "unknown": 1.0, "slat": 53.86666666666667, "elon": -8.8, "s_unknown": 1.0, "sc": 1, "slon": -8.866666666666667}, "821--116": {"c": 147, "elat": 54.8, "unknown": 35.0, "slat": 54.733333333333334, "micro_company": 86.0, "elon": -7.666666666666667, "medium_company": 5.0, "small_company": 21.0, "sc": 2, "s_micro_company": 1.0, "slon": -7.733333333333333, "s_unknown": 1.0}, "807--136": {"c": 26, "elat": 53.86666666666667, "unknown": 6.0, "slat": 53.8, "micro_company": 17.0, "elon": -9.0, "small_company": 3.0, "sc": 1, "slon": -9.066666666666666, "s_unknown": 1.0}, "795--140": {"c": 45, "elat": 53.06666666666667, "unknown": 8.0, "slat": 53.0, "micro_company": 32.0, "elon": -9.266666666666667, "small_company": 5.0, "sc": 2, "s_micro_company": 1.0, "slon": -9.333333333333334, "s_unknown": 1.0}, "807--129": {"c": 6, "elat": 53.86666666666667, "unknown": 1.0, "slat": 53.8, "micro_company": 5.0, "elon": -8.533333333333333, "s_unknown": 1.0, "sc": 1, "slon": -8.6}, "812--129": {"c": 18, "elat": 54.2, "unknown": 7.0, "slat": 54.13333333333333, "micro_company": 9.0, "elon": -8.533333333333333, "small_company": 2.0, "sc": 1, "slon": -8.6, "s_unknown": 1.0}, "828--104": {"c": 64, "elat": 55.266666666666666, "unknown": 20.0, "slat": 55.2, "micro_company": 36.0, "elon": -6.866666666666666, "small_company": 8.0, "sc": 1, "s_micro_company": 1.0, "slon": -6.933333333333334}, "812--120": {"c": 32, "elat": 54.2, "unknown": 18.0, "slat": 54.13333333333333, "micro_company": 10.0, "elon": -7.933333333333334, "small_company": 4.0, "sc": 1, "slon": -8.0, "s_unknown": 1.0}, "809--114": {"c": 33, "elat": 54.0, "unknown": 4.0, "slat": 53.93333333333333, "micro_company": 24.0, "elon": -7.533333333333333, "medium_company": 1.0, "small_company": 4.0, "sc": 1, "slon": -7.6, "s_unknown": 1.0}, "812--127": {"c": 72, "elat": 54.2, "unknown": 15.0, "slat": 54.13333333333333, "micro_company": 41.0, "elon": -8.4, "medium_company": 6.0, "small_company": 10.0, "sc": 2, "s_micro_company": 1.0, "slon": -8.466666666666667, "s_unknown": 1.0}, "806--131": {"large_company": 2.0, "c": 136, "elat": 53.8, "unknown": 23.0, "slat": 53.733333333333334, "micro_company": 82.0, "elon": -8.666666666666666, "medium_company": 1.0, "small_company": 28.0, "sc": 3, "s_micro_company": 1.0, "slon": -8.733333333333333, "s_unknown": 2.0}, "827--115": {"c": 8, "elat": 55.2, "unknown": 2.0, "slat": 55.13333333333333, "micro_company": 5.0, "elon": -7.6, "small_company": 1.0, "sc": 1, "s_micro_company": 1.0, "slon": -7.666666666666667}, "827--114": {"c": 18, "elat": 55.2, "unknown": 3.0, "slat": 55.13333333333333, "micro_company": 13.0, "elon": -7.533333333333333, "medium_company": 1.0, "s_unknown": 1.0, "sc": 1, "slon": -7.6, "small_company": 1.0}, "809--121": {"large_company": 2.0, "c": 329, "elat": 54.0, "unknown": 58.0, "slat": 53.93333333333333, "micro_company": 227.0, "elon": -8.0, "medium_company": 6.0, "small_company": 36.0, "sc": 6, "s_micro_company": 4.0, "slon": -8.066666666666666, "s_unknown": 2.0}, "806--136": {"c": 3, "elat": 53.8, "unknown": 1.0, "slat": 53.733333333333334, "micro_company": 2.0, "elon": -9.0, "sc": 1, "s_micro_company": 1.0, "slon": -9.066666666666666}, "794--133": {"c": 43, "elat": 53.0, "unknown": 14.0, "slat": 52.93333333333333, "micro_company": 26.0, "elon": -8.8, "small_company": 3.0, "sc": 2, "s_micro_company": 1.0, "slon": -8.866666666666667, "s_unknown": 1.0}, "803--151": {"c": 14, "elat": 53.6, "unknown": 4.0, "slat": 53.53333333333333, "micro_company": 10.0, "elon": -10.0, "s_unknown": 1.0, "sc": 1, "slon": -10.066666666666666}, "821--126": {"large_company": 1.0, "c": 62, "elat": 54.8, "unknown": 10.0, "slat": 54.733333333333334, "micro_company": 40.0, "elon": -8.333333333333334, "medium_company": 1.0, "small_company": 10.0, "sc": 1, "s_micro_company": 1.0, "slon": -8.4}, "805--141": {"c": 1, "elat": 53.733333333333334, "unknown": 1.0, "slat": 53.666666666666664, "elon": -9.333333333333334, "s_unknown": 1.0, "sc": 1, "slon": -9.4}, "827--119": {"c": 32, "elat": 55.2, "unknown": 11.0, "slat": 55.13333333333333, "micro_company": 18.0, "elon": -7.866666666666666, "medium_company": 2.0, "s_unknown": 1.0, "sc": 1, "slon": -7.933333333333334, "small_company": 1.0}, "820--119": {"c": 13, "elat": 54.733333333333334, "unknown": 2.0, "slat": 54.666666666666664, "micro_company": 10.0, "elon": -7.866666666666666, "small_company": 1.0, "sc": 1, "s_micro_company": 1.0, "slon": -7.933333333333334}, "811--127": {"c": 93, "elat": 54.13333333333333, "unknown": 18.0, "slat": 54.06666666666667, "micro_company": 61.0, "elon": -8.4, "medium_company": 1.0, "small_company": 13.0, "sc": 1, "s_micro_company": 1.0, "slon": -8.466666666666667}, "811--126": {"c": 11, "elat": 54.13333333333333, "unknown": 3.0, "slat": 54.06666666666667, "micro_company": 8.0, "elon": -8.333333333333334, "s_unknown": 1.0, "sc": 1, "slon": -8.4}, "806--120": {"c": 5, "elat": 53.8, "unknown": 2.0, "slat": 53.733333333333334, "micro_company": 3.0, "elon": -7.933333333333334, "s_unknown": 1.0, "sc": 1, "slon": -8.0}, "811--123": {"c": 24, "elat": 54.13333333333333, "unknown": 4.0, "slat": 54.06666666666667, "micro_company": 17.0, "elon": -8.133333333333333, "medium_company": 3.0, "s_unknown": 1.0, "sc": 1, "slon": -8.2}, "826--124": {"c": 24, "elat": 55.13333333333333, "unknown": 12.0, "slat": 55.06666666666667, "micro_company": 9.0, "elon": -8.2, "medium_company": 2.0, "s_unknown": 1.0, "sc": 1, "slon": -8.266666666666667, "small_company": 1.0}, "806--127": {"c": 196, "elat": 53.8, "unknown": 37.0, "slat": 53.733333333333334, "micro_company": 141.0, "elon": -8.4, "medium_company": 3.0, "s_unknown": 2.0, "sc": 2, "slon": -8.466666666666667, "small_company": 15.0}, "796--123": {"c": 77, "elat": 53.13333333333333, "unknown": 17.0, "slat": 53.06666666666667, "micro_company": 44.0, "elon": -8.133333333333333, "medium_company": 2.0, "small_company": 14.0, "sc": 4, "s_micro_company": 3.0, "slon": -8.2, "s_unknown": 1.0}, "806--145": {"c": 9, "elat": 53.8, "unknown": 3.0, "slat": 53.733333333333334, "micro_company": 6.0, "elon": -9.6, "s_unknown": 1.0, "sc": 1, "slon": -9.666666666666666}, "797--126": {"c": 26, "elat": 53.2, "unknown": 6.0, "slat": 53.13333333333333, "micro_company": 18.0, "elon": -8.333333333333334, "small_company": 2.0, "sc": 1, "slon": -8.4, "s_unknown": 1.0}, "797--127": {"c": 14, "elat": 53.2, "unknown": 1.0, "slat": 53.13333333333333, "micro_company": 12.0, "elon": -8.4, "small_company": 1.0, "sc": 1, "s_micro_company": 1.0, "slon": -8.466666666666667}, "806--141": {"c": 15, "elat": 53.8, "unknown": 3.0, "slat": 53.733333333333334, "micro_company": 12.0, "elon": -9.333333333333334, "s_unknown": 1.0, "sc": 1, "slon": -9.4}, "809--127": {"c": 18, "elat": 54.0, "unknown": 4.0, "slat": 53.93333333333333, "micro_company": 11.0, "elon": -8.4, "s_unknown": 1.0, "sc": 1, "slon": -8.466666666666667, "small_company": 3.0}, "806--143": {"c": 42, "elat": 53.8, "unknown": 8.0, "slat": 53.733333333333334, "micro_company": 32.0, "elon": -9.466666666666667, "medium_company": 1.0, "small_company": 1.0, "sc": 2, "slon": -9.533333333333333, "s_unknown": 2.0}, "806--142": {"large_company": 7.0, "c": 104, "elat": 53.8, "unknown": 25.0, "slat": 53.733333333333334, "micro_company": 62.0, "elon": -9.4, "medium_company": 2.0, "s_unknown": 1.0, "sc": 1, "slon": -9.466666666666667, "small_company": 8.0}, "797--129": {"c": 17, "elat": 53.2, "unknown": 5.0, "slat": 53.13333333333333, "micro_company": 11.0, "elon": -8.533333333333333, "s_unknown": 1.0, "sc": 1, "slon": -8.6, "small_company": 1.0}, "798--136": {"large_company": 2.0, "c": 371, "elat": 53.266666666666666, "unknown": 102.0, "slat": 53.2, "micro_company": 225.0, "elon": -9.0, "medium_company": 4.0, "small_company": 38.0, "sc": 10, "s_micro_company": 7.0, "slon": -9.066666666666666, "s_unknown": 3.0}, "798--137": {"c": 81, "elat": 53.266666666666666, "unknown": 19.0, "slat": 53.2, "micro_company": 53.0, "elon": -9.066666666666666, "medium_company": 1.0, "small_company": 8.0, "sc": 1, "s_micro_company": 1.0, "slon": -9.133333333333333}, "806--121": {"large_company": 5.0, "c": 94, "s_small_company": 1.0, "elat": 53.8, "unknown": 16.0, "slat": 53.733333333333334, "micro_company": 68.0, "elon": -8.0, "small_company": 5.0, "sc": 1, "slon": -8.066666666666666}, "798--135": {"c": 16, "elat": 53.266666666666666, "unknown": 6.0, "slat": 53.2, "micro_company": 9.0, "elon": -8.933333333333334, "small_company": 1.0, "sc": 2, "s_micro_company": 1.0, "slon": -9.0, "s_unknown": 1.0}, "803--128": {"c": 37, "elat": 53.6, "unknown": 11.0, "slat": 53.53333333333333, "micro_company": 24.0, "elon": -8.466666666666667, "small_company": 2.0, "sc": 1, "slon": -8.533333333333333, "s_unknown": 1.0}, "798--133": {"large_company": 2.0, "c": 236, "elat": 53.266666666666666, "unknown": 62.0, "slat": 53.2, "micro_company": 148.0, "elon": -8.8, "medium_company": 4.0, "small_company": 20.0, "sc": 6, "s_micro_company": 1.0, "slon": -8.866666666666667, "s_unknown": 5.0}, "798--130": {"c": 32, "elat": 53.266666666666666, "unknown": 10.0, "slat": 53.2, "micro_company": 20.0, "elon": -8.6, "s_unknown": 1.0, "sc": 1, "slon": -8.666666666666666, "small_company": 2.0}, "798--131": {"c": 101, "s_small_company": 1.0, "elat": 53.266666666666666, "unknown": 23.0, "slat": 53.2, "micro_company": 69.0, "elon": -8.666666666666666, "small_company": 9.0, "sc": 3, "s_micro_company": 2.0, "slon": -8.733333333333333}, "794--139": {"c": 78, "elat": 53.0, "unknown": 18.0, "slat": 52.93333333333333, "micro_company": 49.0, "elon": -9.2, "medium_company": 3.0, "small_company": 8.0, "sc": 4, "s_micro_company": 1.0, "slon": -9.266666666666667, "s_unknown": 3.0}, "798--138": {"c": 37, "elat": 53.266666666666666, "unknown": 11.0, "slat": 53.2, "micro_company": 19.0, "elon": -9.133333333333333, "medium_company": 1.0, "small_company": 6.0, "sc": 3, "s_micro_company": 1.0, "slon": -9.2, "s_unknown": 2.0}, "798--139": {"c": 73, "s_small_company": 1.0, "elat": 53.266666666666666, "unknown": 14.0, "slat": 53.2, "micro_company": 42.0, "elon": -9.2, "medium_company": 1.0, "small_company": 16.0, "sc": 5, "s_micro_company": 2.0, "slon": -9.266666666666667, "s_unknown": 2.0}, "816--124": {"c": 39, "elat": 54.46666666666667, "unknown": 13.0, "slat": 54.4, "micro_company": 22.0, "elon": -8.2, "small_company": 4.0, "sc": 1, "slon": -8.266666666666667, "s_unknown": 1.0}, "817--124": {"large_company": 1.0, "c": 133, "elat": 54.53333333333333, "unknown": 27.0, "slat": 54.46666666666667, "micro_company": 76.0, "elon": -8.2, "medium_company": 6.0, "small_company": 23.0, "sc": 1, "slon": -8.266666666666667, "s_unknown": 1.0}, "812--121": {"c": 7, "elat": 54.2, "unknown": 1.0, "slat": 54.13333333333333, "micro_company": 6.0, "elon": -8.0, "sc": 1, "s_micro_company": 1.0, "slon": -8.066666666666666}, "789--142": {"c": 197, "elat": 52.666666666666664, "unknown": 37.0, "slat": 52.6, "micro_company": 140.0, "elon": -9.4, "medium_company": 6.0, "small_company": 14.0, "sc": 4, "s_micro_company": 3.0, "slon": -9.466666666666667, "s_unknown": 1.0}, "809--134": {"c": 94, "elat": 54.0, "unknown": 21.0, "slat": 53.93333333333333, "micro_company": 61.0, "elon": -8.866666666666667, "medium_company": 1.0, "small_company": 11.0, "sc": 1, "slon": -8.933333333333334, "s_unknown": 1.0}, "809--136": {"large_company": 1.0, "c": 83, "s_small_company": 1.0, "elat": 54.0, "unknown": 13.0, "slat": 53.93333333333333, "micro_company": 55.0, "elon": -9.0, "medium_company": 2.0, "small_company": 12.0, "sc": 1, "slon": -9.066666666666666}, "797--132": {"c": 69, "elat": 53.2, "unknown": 17.0, "slat": 53.13333333333333, "micro_company": 42.0, "elon": -8.733333333333333, "medium_company": 1.0, "small_company": 9.0, "sc": 3, "s_micro_company": 1.0, "slon": -8.8, "s_unknown": 2.0}, "815--128": {"c": 12, "elat": 54.4, "unknown": 5.0, "slat": 54.333333333333336, "micro_company": 7.0, "elon": -8.466666666666667, "s_unknown": 2.0, "sc": 2, "slon": -8.533333333333333}, "825--114": {"large_company": 1.0, "c": 87, "elat": 55.06666666666667, "unknown": 21.0, "slat": 55.0, "micro_company": 56.0, "elon": -7.533333333333333, "medium_company": 2.0, "s_unknown": 2.0, "sc": 2, "slon": -7.6, "small_company": 7.0}, "794--126": {"c": 20, "elat": 53.0, "unknown": 5.0, "slat": 52.93333333333333, "micro_company": 12.0, "elon": -8.333333333333334, "small_company": 3.0, "sc": 1, "s_micro_company": 1.0, "slon": -8.4}, "799--122": {"c": 32, "elat": 53.333333333333336, "unknown": 7.0, "slat": 53.266666666666666, "micro_company": 21.0, "elon": -8.066666666666666, "medium_company": 3.0, "small_company": 1.0, "sc": 3, "s_micro_company": 3.0, "slon": -8.133333333333333}, "799--123": {"c": 177, "elat": 53.333333333333336, "unknown": 36.0, "slat": 53.266666666666666, "micro_company": 113.0, "elon": -8.133333333333333, "medium_company": 4.0, "small_company": 24.0, "sc": 3, "s_micro_company": 3.0, "slon": -8.2}, "803--138": {"c": 32, "elat": 53.6, "unknown": 5.0, "slat": 53.53333333333333, "micro_company": 23.0, "elon": -9.133333333333333, "medium_company": 2.0, "small_company": 2.0, "sc": 1, "slon": -9.2, "s_unknown": 1.0}, "822--125": {"c": 3, "elat": 54.86666666666667, "unknown": 2.0, "slat": 54.8, "micro_company": 1.0, "elon": -8.266666666666667, "sc": 1, "s_micro_company": 1.0, "slon": -8.333333333333334}, "799--129": {"c": 11, "elat": 53.333333333333336, "unknown": 2.0, "slat": 53.266666666666666, "micro_company": 7.0, "elon": -8.533333333333333, "small_company": 2.0, "sc": 1, "s_micro_company": 1.0, "slon": -8.6}, "813--132": {"c": 12, "elat": 54.266666666666666, "unknown": 3.0, "slat": 54.2, "micro_company": 7.0, "elon": -8.733333333333333, "small_company": 2.0, "sc": 1, "s_micro_company": 1.0, "slon": -8.8}, "802--150": {"c": 96, "s_small_company": 1.0, "elat": 53.53333333333333, "unknown": 16.0, "slat": 53.46666666666667, "micro_company": 65.0, "elon": -9.933333333333334, "medium_company": 1.0, "small_company": 14.0, "sc": 4, "s_micro_company": 2.0, "slon": -10.0, "s_unknown": 1.0}, "827--111": {"c": 251, "elat": 55.2, "unknown": 73.0, "slat": 55.13333333333333, "micro_company": 129.0, "elon": -7.333333333333333, "medium_company": 9.0, "small_company": 40.0, "sc": 8, "s_micro_company": 3.0, "slon": -7.4, "s_unknown": 5.0}, "822--115": {"c": 15, "elat": 54.86666666666667, "unknown": 2.0, "slat": 54.8, "micro_company": 13.0, "elon": -7.6, "sc": 1, "s_micro_company": 1.0, "slon": -7.666666666666667}, "814--128": {"c": 136, "elat": 54.333333333333336, "unknown": 36.0, "slat": 54.266666666666666, "micro_company": 80.0, "elon": -8.466666666666667, "medium_company": 4.0, "small_company": 16.0, "sc": 8, "s_micro_company": 3.0, "slon": -8.533333333333333, "s_unknown": 5.0}, "824--112": {"c": 57, "elat": 55.0, "unknown": 17.0, "slat": 54.93333333333333, "micro_company": 28.0, "elon": -7.4, "medium_company": 3.0, "small_company": 9.0, "sc": 2, "slon": -7.466666666666667, "s_unknown": 2.0}, "793--140": {"c": 57, "elat": 52.93333333333333, "unknown": 12.0, "slat": 52.86666666666667, "micro_company": 39.0, "elon": -9.266666666666667, "medium_company": 1.0, "small_company": 5.0, "sc": 2, "s_micro_company": 1.0, "slon": -9.333333333333334, "s_unknown": 1.0}, "807--118": {"c": 47, "elat": 53.86666666666667, "unknown": 14.0, "slat": 53.8, "micro_company": 29.0, "elon": -7.8, "small_company": 4.0, "sc": 3, "s_micro_company": 2.0, "slon": -7.866666666666666, "s_unknown": 1.0}, "814--122": {"c": 69, "elat": 54.333333333333336, "unknown": 15.0, "slat": 54.266666666666666, "micro_company": 46.0, "elon": -8.066666666666666, "medium_company": 2.0, "small_company": 6.0, "sc": 1, "slon": -8.133333333333333, "s_unknown": 1.0}, "814--126": {"large_company": 1.0, "c": 51, "elat": 54.333333333333336, "unknown": 10.0, "slat": 54.266666666666666, "micro_company": 32.0, "elon": -8.333333333333334, "medium_company": 1.0, "small_company": 7.0, "sc": 1, "slon": -8.4, "s_unknown": 1.0}, "814--127": {"large_company": 5.0, "c": 557, "elat": 54.333333333333336, "unknown": 113.0, "slat": 54.266666666666666, "micro_company": 357.0, "elon": -8.4, "medium_company": 15.0, "small_company": 67.0, "sc": 12, "s_micro_company": 6.0, "slon": -8.466666666666667, "s_unknown": 6.0}, "810--127": {"large_company": 6.0, "c": 71, "elat": 54.06666666666667, "unknown": 16.0, "slat": 54.0, "micro_company": 42.0, "elon": -8.4, "medium_company": 2.0, "s_unknown": 1.0, "sc": 1, "slon": -8.466666666666667, "small_company": 5.0}, "813--128": {"c": 18, "elat": 54.266666666666666, "unknown": 3.0, "slat": 54.2, "micro_company": 14.0, "elon": -8.466666666666667, "small_company": 1.0, "sc": 2, "s_micro_company": 1.0, "slon": -8.533333333333333, "s_unknown": 1.0}, "793--127": {"c": 20, "elat": 52.93333333333333, "unknown": 6.0, "slat": 52.86666666666667, "micro_company": 11.0, "elon": -8.4, "small_company": 3.0, "sc": 1, "s_micro_company": 1.0, "slon": -8.466666666666667}, "810--120": {"c": 79, "elat": 54.06666666666667, "unknown": 7.0, "slat": 54.0, "micro_company": 61.0, "elon": -7.933333333333334, "medium_company": 2.0, "small_company": 9.0, "sc": 2, "s_micro_company": 2.0, "slon": -8.0}, "792--132": {"c": 41, "elat": 52.86666666666667, "unknown": 7.0, "slat": 52.8, "micro_company": 32.0, "elon": -8.733333333333333, "small_company": 2.0, "sc": 3, "s_micro_company": 2.0, "slon": -8.8, "s_unknown": 1.0}, "792--133": {"c": 30, "elat": 52.86666666666667, "unknown": 10.0, "slat": 52.8, "micro_company": 18.0, "elon": -8.8, "small_company": 2.0, "sc": 1, "slon": -8.866666666666667, "s_unknown": 1.0}, "792--134": {"large_company": 7.0, "c": 1278, "s_small_company": 1.0, "elat": 52.86666666666667, "unknown": 279.0, "slat": 52.8, "micro_company": 781.0, "elon": -8.866666666666667, "medium_company": 20.0, "small_company": 191.0, "sc": 34, "s_micro_company": 15.0, "slon": -8.933333333333334, "s_unknown": 18.0}, "792--135": {"large_company": 2.0, "c": 83, "elat": 52.86666666666667, "unknown": 15.0, "slat": 52.8, "micro_company": 58.0, "elon": -8.933333333333334, "small_company": 8.0, "sc": 1, "slon": -9.0, "s_unknown": 1.0}, "824--125": {"c": 73, "elat": 55.0, "unknown": 11.0, "slat": 54.93333333333333, "micro_company": 49.0, "elon": -8.266666666666667, "medium_company": 1.0, "small_company": 12.0, "sc": 1, "slon": -8.333333333333334, "s_unknown": 1.0}, "804--133": {"c": 38, "elat": 53.666666666666664, "unknown": 7.0, "slat": 53.6, "micro_company": 28.0, "elon": -8.8, "small_company": 3.0, "sc": 1, "slon": -8.866666666666667, "s_unknown": 1.0}, "804--130": {"c": 9, "elat": 53.666666666666664, "unknown": 3.0, "slat": 53.6, "micro_company": 6.0, "elon": -8.6, "s_unknown": 1.0, "sc": 1, "slon": -8.666666666666666}, "804--131": {"c": 28, "elat": 53.666666666666664, "unknown": 5.0, "slat": 53.6, "micro_company": 17.0, "elon": -8.666666666666666, "small_company": 6.0, "sc": 1, "slon": -8.733333333333333, "s_unknown": 1.0}, "828--108": {"c": 170, "elat": 55.266666666666666, "unknown": 60.0, "slat": 55.2, "micro_company": 95.0, "elon": -7.133333333333334, "medium_company": 3.0, "small_company": 12.0, "sc": 4, "slon": -7.2, "s_unknown": 4.0}, "813--127": {"large_company": 1.0, "c": 186, "elat": 54.266666666666666, "unknown": 37.0, "slat": 54.2, "micro_company": 114.0, "elon": -8.4, "medium_company": 3.0, "small_company": 31.0, "sc": 1, "slon": -8.466666666666667, "s_unknown": 1.0}, "813--126": {"c": 52, "s_small_company": 1.0, "elat": 54.266666666666666, "unknown": 9.0, "slat": 54.2, "micro_company": 30.0, "elon": -8.333333333333334, "medium_company": 1.0, "small_company": 12.0, "sc": 1, "slon": -8.4}, "804--138": {"large_company": 2.0, "c": 192, "elat": 53.666666666666664, "unknown": 28.0, "slat": 53.6, "micro_company": 130.0, "elon": -9.133333333333333, "medium_company": 6.0, "small_company": 26.0, "sc": 3, "s_micro_company": 1.0, "slon": -9.2, "s_unknown": 2.0}, "826--111": {"c": 75, "elat": 55.13333333333333, "unknown": 14.0, "slat": 55.06666666666667, "micro_company": 41.0, "elon": -7.333333333333333, "medium_company": 1.0, "small_company": 19.0, "sc": 1, "slon": -7.4, "s_unknown": 1.0}, "826--112": {"large_company": 1.0, "c": 26, "elat": 55.13333333333333, "unknown": 2.0, "slat": 55.06666666666667, "micro_company": 20.0, "elon": -7.4, "small_company": 3.0, "sc": 2, "s_micro_company": 1.0, "slon": -7.466666666666667, "s_unknown": 1.0}, "792--141": {"c": 65, "elat": 52.86666666666667, "unknown": 7.0, "slat": 52.8, "micro_company": 52.0, "elon": -9.333333333333334, "medium_company": 1.0, "small_company": 5.0, "sc": 1, "s_micro_company": 1.0, "slon": -9.4}, "798--127": {"c": 11, "elat": 53.266666666666666, "unknown": 5.0, "slat": 53.2, "micro_company": 5.0, "elon": -8.4, "medium_company": 1.0, "s_unknown": 1.0, "sc": 1, "slon": -8.466666666666667}, "798--126": {"c": 18, "elat": 53.266666666666666, "unknown": 9.0, "slat": 53.2, "micro_company": 9.0, "elon": -8.333333333333334, "sc": 1, "s_micro_company": 1.0, "slon": -8.4}, "793--133": {"c": 18, "elat": 52.93333333333333, "unknown": 5.0, "slat": 52.86666666666667, "micro_company": 11.0, "elon": -8.8, "small_company": 2.0, "sc": 1, "s_micro_company": 1.0, "slon": -8.866666666666667}, "824--118": {"c": 5, "elat": 55.0, "unknown": 1.0, "slat": 54.93333333333333, "micro_company": 3.0, "elon": -7.8, "small_company": 1.0, "sc": 1, "s_micro_company": 1.0, "slon": -7.866666666666666}, "793--136": {"c": 5, "elat": 52.93333333333333, "unknown": 1.0, "slat": 52.86666666666667, "micro_company": 2.0, "elon": -9.0, "small_company": 2.0, "sc": 1, "slon": -9.066666666666666, "s_unknown": 1.0}, "793--134": {"large_company": 3.0, "c": 70, "elat": 52.93333333333333, "unknown": 17.0, "slat": 52.86666666666667, "micro_company": 38.0, "elon": -8.866666666666667, "medium_company": 1.0, "small_company": 11.0, "sc": 3, "s_micro_company": 2.0, "slon": -8.933333333333334, "s_unknown": 1.0}, "804--121": {"c": 12, "elat": 53.666666666666664, "unknown": 2.0, "slat": 53.6, "micro_company": 9.0, "elon": -8.0, "small_company": 1.0, "sc": 1, "slon": -8.066666666666666, "s_unknown": 1.0}, "804--122": {"c": 204, "elat": 53.666666666666664, "unknown": 49.0, "slat": 53.6, "micro_company": 122.0, "elon": -8.066666666666666, "medium_company": 10.0, "small_company": 23.0, "sc": 3, "s_micro_company": 2.0, "slon": -8.133333333333333, "s_unknown": 1.0}, "792--127": {"c": 16, "elat": 52.86666666666667, "unknown": 4.0, "slat": 52.8, "micro_company": 11.0, "elon": -8.4, "small_company": 1.0, "sc": 3, "s_micro_company": 2.0, "slon": -8.466666666666667, "s_unknown": 1.0}, "792--126": {"c": 124, "elat": 52.86666666666667, "unknown": 26.0, "slat": 52.8, "micro_company": 82.0, "elon": -8.333333333333334, "small_company": 16.0, "sc": 5, "s_micro_company": 1.0, "slon": -8.4, "s_unknown": 4.0}, "824--114": {"c": 42, "elat": 55.0, "unknown": 9.0, "slat": 54.93333333333333, "micro_company": 29.0, "elon": -7.533333333333333, "small_company": 4.0, "sc": 2, "s_micro_company": 1.0, "slon": -7.6, "s_unknown": 1.0}, "824--115": {"large_company": 4.0, "c": 453, "elat": 55.0, "unknown": 98.0, "slat": 54.93333333333333, "micro_company": 261.0, "elon": -7.6, "medium_company": 18.0, "small_company": 72.0, "sc": 11, "s_micro_company": 5.0, "slon": -7.666666666666667, "s_unknown": 6.0}, "802--134": {"c": 37, "elat": 53.53333333333333, "unknown": 7.0, "slat": 53.46666666666667, "micro_company": 29.0, "elon": -8.866666666666667, "medium_company": 1.0, "sc": 1, "s_micro_company": 1.0, "slon": -8.933333333333334}, "808--118": {"c": 13, "elat": 53.93333333333333, "unknown": 1.0, "slat": 53.86666666666667, "micro_company": 12.0, "elon": -7.8, "s_unknown": 1.0, "sc": 1, "slon": -7.866666666666666}, "802--132": {"large_company": 4.0, "c": 396, "elat": 53.53333333333333, "unknown": 70.0, "slat": 53.46666666666667, "micro_company": 266.0, "elon": -8.733333333333333, "medium_company": 8.0, "s_unknown": 7.0, "sc": 8, "s_micro_company": 1.0, "slon": -8.8, "small_company": 48.0}, "802--133": {"large_company": 1.0, "c": 57, "elat": 53.53333333333333, "unknown": 11.0, "slat": 53.46666666666667, "micro_company": 37.0, "elon": -8.8, "medium_company": 4.0, "small_company": 4.0, "sc": 2, "s_micro_company": 2.0, "slon": -8.866666666666667}, "828--106": {"c": 5, "elat": 55.266666666666666, "unknown": 2.0, "slat": 55.2, "micro_company": 2.0, "elon": -7.0, "s_unknown": 1.0, "sc": 1, "slon": -7.066666666666666, "small_company": 1.0}, "799--131": {"large_company": 2.0, "c": 219, "elat": 53.333333333333336, "unknown": 45.0, "slat": 53.266666666666666, "micro_company": 142.0, "elon": -8.666666666666666, "medium_company": 6.0, "small_company": 24.0, "sc": 4, "s_micro_company": 1.0, "slon": -8.733333333333333, "s_unknown": 3.0}, "799--133": {"large_company": 1.0, "c": 355, "elat": 53.333333333333336, "unknown": 63.0, "slat": 53.266666666666666, "micro_company": 242.0, "elon": -8.8, "medium_company": 6.0, "small_company": 43.0, "sc": 9, "s_micro_company": 4.0, "slon": -8.866666666666667, "s_unknown": 5.0}, "799--135": {"large_company": 33.0, "c": 2083, "elat": 53.333333333333336, "unknown": 444.0, "slat": 53.266666666666666, "s_medium_company": 1.0, "micro_company": 1190.0, "elon": -8.933333333333334, "medium_company": 92.0, "small_company": 324.0, "sc": 51, "s_micro_company": 18.0, "slon": -9.0, "s_unknown": 32.0}, "799--134": {"large_company": 29.0, "c": 869, "s_small_company": 1.0, "elat": 53.333333333333336, "unknown": 161.0, "slat": 53.266666666666666, "micro_company": 543.0, "elon": -8.866666666666667, "medium_company": 23.0, "small_company": 113.0, "sc": 13, "s_micro_company": 7.0, "slon": -8.933333333333334, "s_unknown": 5.0}, "799--137": {"c": 45, "elat": 53.333333333333336, "unknown": 16.0, "slat": 53.266666666666666, "micro_company": 27.0, "elon": -9.066666666666666, "s_unknown": 2.0, "sc": 2, "slon": -9.133333333333333, "small_company": 2.0}, "799--136": {"large_company": 3.0, "c": 564, "elat": 53.333333333333336, "unknown": 145.0, "slat": 53.266666666666666, "micro_company": 348.0, "elon": -9.0, "medium_company": 7.0, "small_company": 61.0, "sc": 24, "s_micro_company": 13.0, "slon": -9.066666666666666, "s_unknown": 11.0}, "818--123": {"c": 19, "elat": 54.6, "unknown": 7.0, "slat": 54.53333333333333, "micro_company": 11.0, "elon": -8.133333333333333, "s_unknown": 1.0, "sc": 1, "slon": -8.2, "small_company": 1.0}, "801--142": {"c": 2, "elat": 53.46666666666667, "slat": 53.4, "micro_company": 2.0, "elon": -9.4, "sc": 1, "s_micro_company": 1.0, "slon": -9.466666666666667}, "804--150": {"c": 31, "elat": 53.666666666666664, "unknown": 5.0, "slat": 53.6, "micro_company": 22.0, "elon": -9.933333333333334, "medium_company": 2.0, "small_company": 2.0, "sc": 2, "slon": -10.0, "s_unknown": 2.0}, "810--131": {"c": 22, "elat": 54.06666666666667, "unknown": 6.0, "slat": 54.0, "micro_company": 12.0, "elon": -8.666666666666666, "medium_company": 1.0, "small_company": 3.0, "sc": 1, "s_micro_company": 1.0, "slon": -8.733333333333333}, "810--130": {"c": 52, "elat": 54.06666666666667, "unknown": 6.0, "slat": 54.0, "micro_company": 38.0, "elon": -8.6, "medium_company": 2.0, "small_company": 6.0, "sc": 2, "s_micro_company": 2.0, "slon": -8.666666666666666}, "802--127": {"c": 57, "elat": 53.53333333333333, "unknown": 18.0, "slat": 53.46666666666667, "micro_company": 33.0, "elon": -8.4, "s_unknown": 1.0, "sc": 1, "slon": -8.466666666666667, "small_company": 6.0}, "829--107": {"c": 32, "elat": 55.333333333333336, "unknown": 12.0, "slat": 55.266666666666666, "micro_company": 17.0, "elon": -7.066666666666666, "small_company": 3.0, "sc": 1, "s_micro_company": 1.0, "slon": -7.133333333333334}, "802--121": {"c": 64, "elat": 53.53333333333333, "unknown": 19.0, "slat": 53.46666666666667, "micro_company": 35.0, "elon": -8.0, "medium_company": 2.0, "s_unknown": 1.0, "sc": 2, "s_micro_company": 1.0, "slon": -8.066666666666666, "small_company": 8.0}, "802--120": {"c": 36, "elat": 53.53333333333333, "unknown": 10.0, "slat": 53.46666666666667, "micro_company": 25.0, "elon": -7.933333333333334, "s_unknown": 1.0, "sc": 1, "slon": -8.0, "small_company": 1.0}, "829--108": {"c": 20, "elat": 55.333333333333336, "unknown": 9.0, "slat": 55.266666666666666, "micro_company": 7.0, "elon": -7.133333333333334, "small_company": 4.0, "sc": 1, "slon": -7.2, "s_unknown": 1.0}, "802--128": {"c": 44, "elat": 53.53333333333333, "unknown": 14.0, "slat": 53.46666666666667, "micro_company": 27.0, "elon": -8.466666666666667, "small_company": 3.0, "sc": 2, "s_micro_company": 1.0, "slon": -8.533333333333333, "s_unknown": 1.0}, "803--146": {"c": 2, "elat": 53.6, "unknown": 1.0, "slat": 53.53333333333333, "micro_company": 1.0, "elon": -9.666666666666666, "s_unknown": 1.0, "sc": 1, "slon": -9.733333333333333}, "813--149": {"c": 102, "elat": 54.266666666666666, "unknown": 24.0, "slat": 54.2, "micro_company": 69.0, "elon": -9.866666666666667, "medium_company": 1.0, "small_company": 8.0, "sc": 3, "s_micro_company": 2.0, "slon": -9.933333333333334, "s_unknown": 1.0}, "807--142": {"large_company": 4.0, "c": 320, "elat": 53.86666666666667, "unknown": 72.0, "slat": 53.8, "micro_company": 213.0, "elon": -9.4, "medium_company": 2.0, "small_company": 29.0, "sc": 5, "s_micro_company": 2.0, "slon": -9.466666666666667, "s_unknown": 3.0}, "807--143": {"c": 63, "elat": 53.86666666666667, "unknown": 17.0, "slat": 53.8, "s_medium_company": 1.0, "micro_company": 35.0, "elon": -9.466666666666667, "medium_company": 2.0, "small_company": 9.0, "sc": 1, "slon": -9.533333333333333}, "800--138": {"c": 38, "elat": 53.4, "unknown": 15.0, "slat": 53.333333333333336, "micro_company": 20.0, "elon": -9.133333333333333, "s_unknown": 2.0, "sc": 2, "slon": -9.2, "small_company": 3.0}, "790--133": {"large_company": 105.0, "c": 685, "elat": 52.733333333333334, "unknown": 108.0, "slat": 52.666666666666664, "micro_company": 247.0, "elon": -8.8, "medium_company": 145.0, "small_company": 80.0, "sc": 5, "s_micro_company": 1.0, "slon": -8.866666666666667, "s_unknown": 4.0}, "790--130": {"c": 14, "elat": 52.733333333333334, "unknown": 5.0, "slat": 52.666666666666664, "micro_company": 7.0, "elon": -8.6, "small_company": 2.0, "sc": 2, "slon": -8.666666666666666, "s_unknown": 2.0}, "790--139": {"large_company": 1.0, "c": 24, "elat": 52.733333333333334, "unknown": 4.0, "slat": 52.666666666666664, "micro_company": 15.0, "elon": -9.2, "small_company": 4.0, "sc": 1, "slon": -9.266666666666667, "s_unknown": 1.0}, "801--135": {"c": 90, "elat": 53.46666666666667, "unknown": 18.0, "slat": 53.4, "micro_company": 67.0, "elon": -8.933333333333334, "small_company": 5.0, "sc": 2, "s_micro_company": 1.0, "slon": -9.0, "s_unknown": 1.0}, "798--140": {"c": 6, "elat": 53.266666666666666, "unknown": 2.0, "slat": 53.2, "micro_company": 4.0, "elon": -9.266666666666667, "s_unknown": 1.0, "sc": 1, "slon": -9.333333333333334}, "798--142": {"large_company": 4.0, "c": 49, "elat": 53.266666666666666, "unknown": 11.0, "slat": 53.2, "micro_company": 24.0, "elon": -9.4, "medium_company": 2.0, "small_company": 8.0, "sc": 3, "s_micro_company": 1.0, "slon": -9.466666666666667, "s_unknown": 2.0}, "801--133": {"c": 96, "elat": 53.46666666666667, "unknown": 21.0, "slat": 53.4, "micro_company": 58.0, "elon": -8.8, "medium_company": 1.0, "small_company": 16.0, "sc": 2, "s_micro_company": 2.0, "slon": -8.866666666666667}, "799--143": {"c": 16, "elat": 53.333333333333336, "unknown": 4.0, "slat": 53.266666666666666, "micro_company": 9.0, "elon": -9.466666666666667, "small_company": 3.0, "sc": 1, "s_micro_company": 1.0, "slon": -9.533333333333333}}